dployr/__init__.py
dployr-1.0.0.dist-info/METADATA
dployr-1.0.0.dist-info/RECORD
dployr-1.0.0.dist-info/WHEEL
dployr-1.0.0.dist-info/entry_points.txt
dployr-1.0.0.dist-info/top_level.txt
